signal_edges/__init__.py
signal_edges/definitions.py
signal_edges/exceptions.py
signal_edges/plotter/__init__.py
signal_edges/plotter/definitions.py
signal_edges/plotter/plotter.py
signal_edges/plotter/style/style.mplstyle
signal_edges/signal/__init__.py
signal_edges/signal/edges/__init__.py
signal_edges/signal/edges/definitions.py
signal_edges/signal/edges/edges.py
signal_edges/signal/filters/__init__.py
signal_edges/signal/filters/bessel.py
signal_edges/signal/filters/butterworth.py
signal_edges/signal/filters/elliptic.py
signal_edges/signal/filters/filters.py
signal_edges/signal/generator/__init__.py
signal_edges/signal/generator/generator.py
signal_edges/signal/sample/__init__.py
signal_edges/signal/sample/sample.py
signal_edges/signal/signal.py
signal_edges/signal/state_levels/__init__.py
signal_edges/signal/state_levels/definitions.py
signal_edges/signal/state_levels/state_levels.py
signal_edges/signal/voltage_signal.py
python_signal_edges-1.0.5.dist-info/LICENSE
python_signal_edges-1.0.5.dist-info/METADATA
python_signal_edges-1.0.5.dist-info/WHEEL
python_signal_edges-1.0.5.dist-info/RECORD
