Metadata-Version: 2.1
Name: python-signal-edges
Version: 1.0.5
Summary: Extract state levels and edges from signals, among others
Home-page: https://github.com/dmg0345/python-signal-edges
License: MIT
Keywords: python,signal,edges,automation,hardware,pwm,acquisition
Author: Diego Martinez
Author-email: dmg0345@gmail.com
Requires-Python: >=3.10,<4.0
Classifier: License :: OSI Approved :: MIT License
Classifier: Programming Language :: Python :: 3
Classifier: Programming Language :: Python :: 3.10
Classifier: Programming Language :: Python :: 3.11
Requires-Dist: matplotlib (>=3.8.2)
Requires-Dist: numpy (>=1.26.0)
Requires-Dist: scipy (>=1.12.0)
Project-URL: Documentation, https://dmg0345-python-signal-edges.netlify.app/
Project-URL: Repository, https://github.com/dmg0345/python-signal-edges
